Metadata-Version: 1.0
Name: Tempita
Version: 0.3
Summary: A very small text templating language
Home-page: http://pythonpaste.org/tempita/
Author: Ian Bicking
Author-email: ianb@colorstudy.com
License: MIT
Keywords: templating template language html
Platform: UNKNOWN
Classifier: Development Status :: 4 - Beta
Classifier: Intended Audience :: Developers
Classifier: License :: OSI Approved :: MIT License
Classifier: Topic :: Text Processing
